README.md
setup.py
tests.sh
.meta/packages
.meta/pylintrc
txamqp_ext/__init__.py
txamqp_ext/factory.py
txamqp_ext/interfaces.py
txamqp_ext/protocol.py
txamqp_ext.egg-info/PKG-INFO
txamqp_ext.egg-info/SOURCES.txt
txamqp_ext.egg-info/dependency_links.txt
txamqp_ext.egg-info/not-zip-safe
txamqp_ext.egg-info/requires.txt
txamqp_ext.egg-info/top_level.txt
txamqp_ext/spec/amqp0-8.xml
txamqp_ext/spec/amqp0-9-1.xml
txamqp_ext/test/__init__.py
txamqp_ext/test/test_basic.py
txamqp_ext/test/test_encoding.py
txamqp_ext/test/test_factory.py
txamqp_ext/test/test_protocol.py
txamqp_ext/test/test_push_factory.py