Metadata-Version: 1.0
Name: txamqp-ext
Version: 0.3.1
Summary: txAMQP extended
Home-page: https://github.com/cybergrind/txamqp_ext
Author: cybergrind
Author-email: cybergrind@gmail.com
License: LGPL
Keywords: twisted amqp txamqp
Platform: UNKNOWN
